[
    {
        "index": 1,
        "infos": [
            {
                "基本信息-姓名": "李勇",
                "基本信息-手机号码": "",
                "基本信息-邮箱": "",
                "基本信息-地区": "",
                "基本信息-详细地址": "",
                "基本信息-性别": "",
                "基本信息-年龄": "",
                "基本信息-生日": "",
                "咨询类型": [
                    "答疑"
                ],
                "意向产品": [],
                "购买异议点": [],
                "客户预算-预算是否充足": "",
                "客户预算-总体预算金额": "",
                "客户预算-预算明细": [],
                "竞品信息": [],
                "客户是否有意向": "有意向",
                "客户是否有卡点": "无卡点",
                "客户购买阶段": "方案交流",
                "下一步跟进计划-参与人": [],
                "下一步跟进计划-时间点": "",
                "下一步跟进计划-具体事项": ""
            }
        ]
    },
    {
        "index": 2,
        "infos": [
            {
                "基本信息-姓名": "孙洋2",
                "基本信息-手机号码": "",
                "基本信息-邮箱": "",
                "基本信息-地区": "",
                "基本信息-详细地址": "",
                "基本信息-性别": "",
                "基本信息-年龄": "",
                "基本信息-生日": "",
                "咨询类型": [
                    "对接有赞"
                ],
                "意向产品": [],
                "购买异议点": [
                    "客户通不支持对接",
                    "额外收费问题"
                ],
                "客户预算-预算是否充足": "",
                "客户预算-总体预算金额": "",
                "客户预算-预算明细": [],
                "竞品信息": [
                    "weisheng"
                ],
                "客户是否有意向": "有意向",
                "客户是否有卡点": "无卡点",
                "客户购买阶段": "方案交流",
                "下一步跟进计划-参与人": [
                    "赵杰5"
                ],
                "下一步跟进计划-时间点": "",
                "下一步跟进计划-具体事项": "评估工作量和报价"
            }
        ]
    },
    {
        "index": 3,
        "infos": []
    },
    {
        "index": 4,
        "infos": [
            {
                "基本信息-姓名": "郑杰1",
                "基本信息-手机号码": "",
                "基本信息-邮箱": "",
                "基本信息-地区": "湖南省合肥市",
                "基本信息-详细地址": "",
                "基本信息-性别": "",
                "基本信息-年龄": "",
                "基本信息-生日": "",
                "咨询类型": [
                    "答疑"
                ],
                "意向产品": [],
                "购买异议点": "",
                "客户预算-是否充足": "",
                "客户预算-总体预算金额": "",
                "客户预算-预算明细": "",
                "竞品信息": "",
                "客户是否有意向": "有意向",
                "客户是否有卡点": "无卡点",
                "客户购买阶段": "方案交流",
                "下一步跟进计划-参与人": [],
                "下一步跟进计划-时间点": "",
                "下一步跟进计划-具体事项": ""
            }
        ]
    },
    {
        "index": 5,
        "infos": [
            {
                "基本信息-姓名": "赵艳2",
                "基本信息-手机号码": "",
                "基本信息-邮箱": "",
                "基本信息-地区": "湖南省合肥市",
                "基本信息-详细地址": "",
                "基本信息-性别": "",
                "基本信息-年龄": "",
                "基本信息-生日": "",
                "咨询类型": [
                    "数字化运营",
                    "私域运营"
                ],
                "意向产品": [],
                "购买异议点": [],
                "客户预算-预算是否充足": "",
                "客户预算-总体预算金额": "",
                "客户预算-预算明细": "",
                "竞品信息": "",
                "客户是否有意向": "有意向",
                "客户是否有卡点": "无卡点",
                "客户购买阶段": "方案交流",
                "下一步跟进计划-参与人": [
                    "王勇7"
                ],
                "下一步跟进计划-时间点": "",
                "下一步跟进计划-具体事项": "安排workshop，对接需求"
            }
        ]
    }
]